pyvotal_tracker/__init__.py
pyvotal_tracker/client.py
pyvotal_tracker/pivotal.py
pyvotal_tracker-0.0.6.dist-info/LICENSE
pyvotal_tracker-0.0.6.dist-info/METADATA
pyvotal_tracker-0.0.6.dist-info/WHEEL
pyvotal_tracker-0.0.6.dist-info/top_level.txt
pyvotal_tracker-0.0.6.dist-info/RECORD
