Metadata-Version: 2.1
Name: pyvotal-tracker
Version: 0.0.6
Summary: Pivotal Tracker API module
Home-page: UNKNOWN
Author: Alireza Tajik
Author-email: alireza7192@gmail.com
License: MIT
Platform: UNKNOWN
Requires-Dist: requests
